causal_inference/__init__.py
causal_inference/__main__.py
causal_inference/src/__init__.py
causal_inference/src/uc_scm/__init__.py
causal_inference/src/uc_scm/scm.py
causal_inference/util/__init__.py
causal_inference/util/data_input_loader.py
causal_inference-0.0.4.dist-info/LICENSE
causal_inference-0.0.4.dist-info/METADATA
causal_inference-0.0.4.dist-info/WHEEL
causal_inference-0.0.4.dist-info/top_level.txt
causal_inference-0.0.4.dist-info/RECORD
