Metadata-Version: 2.1
Name: causal-inference
Version: 0.0.4
Summary: Causal Inference
Home-page: https://github.com/ga74kud/causal_inference
Author: Michael Hartmann
Author-email: michael.hartmann@v2c2.at
License: GNU GENERAL PUBLIC LICENSE
Platform: UNKNOWN
Requires-Dist: scipy
Requires-Dist: numpy
Requires-Dist: matplotlib
Requires-Dist: argparse
Requires-Dist: python-igraph
Requires-Dist: pycairo
Requires-Dist: plotly
Requires-Dist: pandas
Requires-Dist: sympy
